flake8_params/__init__.py
flake8_params/py.typed
flake8_params-0.3.1.dist-info/LICENSE
flake8_params-0.3.1.dist-info/METADATA
flake8_params-0.3.1.dist-info/WHEEL
flake8_params-0.3.1.dist-info/entry_points.txt
flake8_params-0.3.1.dist-info/RECORD
