Metadata-Version: 2.2
Name: flake8-params
Version: 0.3.1
Summary: A flake8 plugin which checks for mismatches between function signatures and docstring params.
Author-email: Dominic Davis-Foster <dominic@davis-foster.co.uk>
License: MIT
Keywords: documentation,flake8
Home-page: https://github.com/python-formate/flake8-params
Project-URL: Issue Tracker, https://github.com/python-formate/flake8-params/issues
Project-URL: Source Code, https://github.com/python-formate/flake8-params
Project-URL: Documentation, https://flake8-params.readthedocs.io/en/latest
Platform: Windows
Platform: macOS
Platform: Linux
Classifier: Development Status :: 4 - Beta
Classifier: Framework :: Flake8
Classifier: Intended Audience :: Developers
Classifier: License :: OSI Approved :: MIT License
Classifier: Operating System :: OS Independent
Classifier: Programming Language :: Python
Classifier: Programming Language :: Python :: 3 :: Only
Classifier: Programming Language :: Python :: 3.8
Classifier: Programming Language :: Python :: 3.9
Classifier: Programming Language :: Python :: 3.10
Classifier: Programming Language :: Python :: 3.11
Classifier: Programming Language :: Python :: 3.12
Classifier: Programming Language :: Python :: 3.13
Classifier: Programming Language :: Python :: Implementation :: CPython
Classifier: Topic :: Utilities
Classifier: Typing :: Typed
Requires-Python: >=3.8
Requires-Dist: flake8>=3.7
Requires-Dist: flake8-helper>=0.1.1
